ursinanetworking/__init__.py
ursinanetworking/easyursinanetworking.py
ursinanetworking/replicated_2.py
ursinanetworking/test_cl.py
ursinanetworking/test_sv.py
ursinanetworking/ursinanetworking.py
UrsinaNetworking-2.1.5.dist-info/LICENSE
UrsinaNetworking-2.1.5.dist-info/METADATA
UrsinaNetworking-2.1.5.dist-info/WHEEL
UrsinaNetworking-2.1.5.dist-info/top_level.txt
UrsinaNetworking-2.1.5.dist-info/RECORD
