Metadata-Version: 2.1
Name: UrsinaNetworking
Version: 2.1.5
Summary: A high level API for networking !
Home-page: https://github.com/kstzl/UrsinaNetworking
Author: K3#4869 & Squiggle#1385
Author-email: kevin.stoetzel@gmail.com
License: MIT
Keywords: ursina,networking,sockets
Platform: UNKNOWN
License-File: LICENSE
